karel_the_robot/__init__.py
karel_the_robot/karel_the_robot.py
karel_the_robot-1.1.1.dist-info/METADATA
karel_the_robot-1.1.1.dist-info/WHEEL
karel_the_robot-1.1.1.dist-info/top_level.txt
karel_the_robot-1.1.1.dist-info/RECORD
