Metadata-Version: 2.1
Name: karel-the-robot
Version: 1.1.1
Summary: Unofficial port of Karel the Robot to Python
Home-page: https://github.com/cjbell630/Karel_the_Robot-Python
Author: Connor Bell
Author-email: ronnoclleb@gmail.com
Requires-Dist: numpy
Requires-Dist: pygame
